notip/__init__.py
notip/posthoc_fmri.py
notip-0.1.6.dist-info/METADATA
notip-0.1.6.dist-info/WHEEL
notip-0.1.6.dist-info/top_level.txt
notip-0.1.6.dist-info/RECORD
