Metadata-Version: 2.1
Name: notip
Version: 0.1.6
Summary: Nonparametric True Discovery Proportion control for brain imaging
Home-page: https://github.com/alexblnn/Notip
Download-URL: https://github.com/alexblnn/Notip/releases/download/Notip_OHBM_v2/notip-0.1.2.tar.gz
Author: Alexandre Blain
Author-email: alexandre.blain@inria.fr
Classifier: Programming Language :: Python :: 3.7
Classifier: License :: OSI Approved :: GNU General Public License v3 (GPLv3)
Requires-Dist: numpy (>=1.15.0)
Requires-Dist: scipy (>=1.0.0)
Requires-Dist: joblib (>=1.0.1)
Requires-Dist: scikit-learn (>=0.22)
Requires-Dist: nilearn (>=0.10.0)
Requires-Dist: matplotlib (>=3.3.0)
Requires-Dist: sanssouci
Requires-Dist: pandas
Requires-Dist: joblib
Requires-Dist: tqdm
